odoo/addons/microsoft_outlook_single_tenant/README.rst
odoo/addons/microsoft_outlook_single_tenant/__init__.py
odoo/addons/microsoft_outlook_single_tenant/__manifest__.py
odoo/addons/microsoft_outlook_single_tenant/hooks.py
odoo/addons/microsoft_outlook_single_tenant/i18n/microsoft_outlook_single_tenant.pot
odoo/addons/microsoft_outlook_single_tenant/models/__init__.py
odoo/addons/microsoft_outlook_single_tenant/models/microsoft_outlook_mixin.py
odoo/addons/microsoft_outlook_single_tenant/models/res_config_settings.py
odoo/addons/microsoft_outlook_single_tenant/readme/CONFIGURE.rst
odoo/addons/microsoft_outlook_single_tenant/readme/CONTRIBUTORS.rst
odoo/addons/microsoft_outlook_single_tenant/readme/DESCRIPTION.rst
odoo/addons/microsoft_outlook_single_tenant/static/description/icon.png
odoo/addons/microsoft_outlook_single_tenant/static/description/index.html
odoo/addons/microsoft_outlook_single_tenant/tests/__init__.py
odoo/addons/microsoft_outlook_single_tenant/tests/test_fetchmail_outlook.py
odoo/addons/microsoft_outlook_single_tenant/views/res_config_settings_views.xml
odoo14_addon_microsoft_outlook_single_tenant-14.0.2.0.0.dist-info/METADATA
odoo14_addon_microsoft_outlook_single_tenant-14.0.2.0.0.dist-info/WHEEL
odoo14_addon_microsoft_outlook_single_tenant-14.0.2.0.0.dist-info/top_level.txt
odoo14_addon_microsoft_outlook_single_tenant-14.0.2.0.0.dist-info/RECORD
